odoo/addons/company_country/README.rst
odoo/addons/company_country/__init__.py
odoo/addons/company_country/__manifest__.py
odoo/addons/company_country/data/res_config.xml
odoo/addons/company_country/i18n/company_country.pot
odoo/addons/company_country/migrations/12.0.1.0.2/pre-migration.py
odoo/addons/company_country/models/__init__.py
odoo/addons/company_country/models/res_config.py
odoo/addons/company_country/readme/CONFIGURE.rst
odoo/addons/company_country/readme/CONTRIBUTORS.rst
odoo/addons/company_country/readme/CREDITS.rst
odoo/addons/company_country/readme/DESCRIPTION.rst
odoo/addons/company_country/readme/INSTALL.rst
odoo/addons/company_country/readme/USAGE.rst
odoo/addons/company_country/static/description/icon.png
odoo/addons/company_country/static/description/index.html
odoo/addons/company_country/tests/__init__.py
odoo/addons/company_country/tests/test_company_country.py
odoo12_addon_company_country-12.0.1.2.1.dist-info/METADATA
odoo12_addon_company_country-12.0.1.2.1.dist-info/WHEEL
odoo12_addon_company_country-12.0.1.2.1.dist-info/top_level.txt
odoo12_addon_company_country-12.0.1.2.1.dist-info/RECORD
